drime/__init__.py
drime/drime.py
drime-0.1.1.dist-info/METADATA
drime-0.1.1.dist-info/WHEEL
drime-0.1.1.dist-info/top_level.txt
drime-0.1.1.dist-info/RECORD
