Metadata-Version: 2.1
Name: drime
Version: 0.1.1
Summary: A Python package for interacting with the Drime API.
Home-page: https://github.com/PainDe0Mie/drime
Author: PainDe0Mie
Author-email: painde0mie@example.com
Classifier: Development Status :: 3 - Alpha
Classifier: Intended Audience :: Developers
Classifier: License :: OSI Approved :: MIT License
Classifier: Programming Language :: Python :: 3
Classifier: Programming Language :: Python :: 3.8
Requires-Dist: requests
